libsncompress/__init__.py
libsncompress/base.py
libsncompress/binning.py
libsncompress/evaluator.py
libsncompress/simplecache.py
libsncompress-0.0.8.data/data/share/libsncompress/table_A1.txt
libsncompress-0.0.8.data/data/share/libsncompress/table_A2.txt
libsncompress-0.0.8.data/scripts/jlacompress
libsncompress-0.0.8.dist-info/DESCRIPTION.rst
libsncompress-0.0.8.dist-info/METADATA
libsncompress-0.0.8.dist-info/RECORD
libsncompress-0.0.8.dist-info/WHEEL
libsncompress-0.0.8.dist-info/metadata.json
libsncompress-0.0.8.dist-info/top_level.txt
