Metadata-Version: 2.0
Name: libsncompress
Version: 0.0.8
Summary: Compress JLA-like supernova data
Home-page: https://gitlab.com/congma/libsncompress/
Author: Cong Ma
Author-email: cong.ma@obspm.fr
License: BSD
Platform: UNKNOWN
Classifier: Development Status :: 4 - Beta
Classifier: Environment :: Console
Classifier: Intended Audience :: Science/Research
Classifier: License :: OSI Approved :: BSD License
Classifier: Operating System :: OS Independent
Classifier: Programming Language :: Python :: 2.7
Classifier: Programming Language :: Python :: 3.6
Classifier: Programming Language :: Python :: 3.7
Classifier: Programming Language :: Python :: Implementation :: CPython
Classifier: Topic :: Scientific/Engineering :: Astronomy
Classifier: Topic :: Scientific/Engineering :: Information Analysis
Classifier: Topic :: Software Development :: Libraries :: Python Modules
Provides: libsncompress
Requires-Python: >=2.7, !=3.0.*, !=3.1.*, !=3.2.*, !=3.3.*, !=3.4.*, !=3.5.*, <3.8
Requires-Dist: six
Requires-Dist: numpy (>=1.6.0)
Requires-Dist: scipy (>=0.11.0)
Requires-Dist: astropy
Requires-Dist: cachetools
